ae/deep.py
ae_deep-0.3.13.dist-info/LICENSE.md
ae_deep-0.3.13.dist-info/METADATA
ae_deep-0.3.13.dist-info/WHEEL
ae_deep-0.3.13.dist-info/top_level.txt
ae_deep-0.3.13.dist-info/zip-safe
ae_deep-0.3.13.dist-info/RECORD
